edwh_bundler_plugin/__about__.py
edwh_bundler_plugin/__init__.py
edwh_bundler_plugin/bundler_plugin.py
edwh_bundler_plugin/css.py
edwh_bundler_plugin/js.py
edwh_bundler_plugin/lazy.py
edwh_bundler_plugin/shared.py
edwh_bundler_plugin/js/ts_loader.js
edwh_bundler_plugin-4.0.1.dist-info/METADATA
edwh_bundler_plugin-4.0.1.dist-info/WHEEL
edwh_bundler_plugin-4.0.1.dist-info/entry_points.txt
edwh_bundler_plugin-4.0.1.dist-info/RECORD
