Metadata-Version: 2.4
Name: edwh-bundler-plugin
Version: 4.0.1
Summary: Python-only static file (js, css) bundler for `edwh`
Project-URL: Documentation, https://github.com/educationwarehouse/edwh-bundler-plugin#readme
Project-URL: Issues, https://github.com/educationwarehouse/edwh-bundler-plugin/issues
Project-URL: Source, https://github.com/educationwarehouse/edwh-bundler-plugin
Author-email: Robin van der Noord <robin.vdn@educationwarehouse.nl>, Remco Boerma <remco.b@educationwarehouse.nl>
Classifier: Development Status :: 4 - Beta
Classifier: Programming Language :: Python
Classifier: Programming Language :: Python :: 3.10
Classifier: Programming Language :: Python :: 3.11
Classifier: Programming Language :: Python :: 3.12
Classifier: Programming Language :: Python :: Implementation :: CPython
Classifier: Programming Language :: Python :: Implementation :: PyPy
Requires-Python: >=3.10
Requires-Dist: configuraptor>=1.28.0
Requires-Dist: dukpy
Requires-Dist: edwh>=0.56.6
Requires-Dist: python-dotenv
Requires-Dist: pyyaml
Requires-Dist: requests
Requires-Dist: rjsmin
Requires-Dist: sassquatch>=1.0.1
Requires-Dist: tomlkit
Provides-Extra: dev
Requires-Dist: hatch; extra == 'dev'
Requires-Dist: pytest; extra == 'dev'
Requires-Dist: python-semantic-release<8; extra == 'dev'
